doscon_tb_api/__init__.py
doscon_tb_api/doscon_tb_api.py
doscon_tb_api/test/__init__.py
doscon_tb_api/test/test_doscon_tb_api.py
doscon_tb_api-0.1.8.dist-info/LICENSE
doscon_tb_api-0.1.8.dist-info/METADATA
doscon_tb_api-0.1.8.dist-info/WHEEL
doscon_tb_api-0.1.8.dist-info/top_level.txt
doscon_tb_api-0.1.8.dist-info/RECORD
