Metadata-Version: 2.1
Name: doscon_tb_api
Version: 0.1.8
Summary: minmalistic library to connect to the thingsboard API.
Home-page: https://github.com/DOSCON-development/tb_api
Author: Aleksander Hykkerud
Author-email: lorithai@gmail.com
Classifier: Programming Language :: Python :: 3
Classifier: License :: OSI Approved :: MIT License
Classifier: Operating System :: OS Independent
Requires-Python: >=3.6
License-File: LICENSE
